snakebids/__init__.py
snakebids/__init__.pyi
snakebids/_warningformat.py
snakebids/admin.py
snakebids/app.py
snakebids/cli.py
snakebids/exceptions.py
snakebids/py.typed
snakebids/snakemake_compat.py
snakebids/snakemake_compat.pyi
snakebids/types.py
snakebids/bidsapp/__init__.py
snakebids/bidsapp/__init__.pyi
snakebids/bidsapp/args.py
snakebids/bidsapp/hook.py
snakebids/bidsapp/hookspecs.py
snakebids/bidsapp/run.py
snakebids/core/__init__.py
snakebids/core/__init__.pyi
snakebids/core/_querying.py
snakebids/core/datasets.py
snakebids/core/filtering.py
snakebids/core/input_generation.py
snakebids/io/__init__.py
snakebids/io/__init__.pyi
snakebids/io/config.py
snakebids/io/console.py
snakebids/io/printing.py
snakebids/io/yaml.py
snakebids/jinja2_ext/__init__.py
snakebids/jinja2_ext/__init__.pyi
snakebids/jinja2_ext/colorama.py
snakebids/jinja2_ext/format_dep_spec.py
snakebids/jinja2_ext/snakebids_version.py
snakebids/jinja2_ext/toml_encode.py
snakebids/jinja2_ext/vcs.py
snakebids/paths/__init__.py
snakebids/paths/__init__.pyi
snakebids/paths/_config.py
snakebids/paths/_factory.py
snakebids/paths/_presets.py
snakebids/paths/_utils.py
snakebids/paths/specs.py
snakebids/paths/specs.pyi
snakebids/paths/_templates/__init__.py
snakebids/paths/_templates/__init__.pyi
snakebids/paths/_templates/spec_func.py
snakebids/paths/resources/__init__.py
snakebids/paths/resources/__init__.pyi
snakebids/paths/resources/spec.0.0.0.yaml
snakebids/paths/resources/spec.0.11.0.yaml
snakebids/paths/resources/spec.0.15.0.yaml
snakebids/plugins/__init__.py
snakebids/plugins/__init__.pyi
snakebids/plugins/base.py
snakebids/plugins/bidsargs.py
snakebids/plugins/cli_config.py
snakebids/plugins/component_edit.py
snakebids/plugins/pybidsdb.py
snakebids/plugins/snakemake.py
snakebids/plugins/validator.py
snakebids/plugins/version.py
snakebids/project_template/.gitignore
snakebids/project_template/README.md.jinja
snakebids/project_template/copier.yaml
snakebids-0.15.0.dist-info/METADATA
snakebids-0.15.0.dist-info/WHEEL
snakebids-0.15.0.dist-info/entry_points.txt
snakebids-0.15.0.dist-info/licenses/LICENSE
snakebids-0.15.0.dist-info/RECORD
