Metadata-Version: 2.4
Name: snakebids
Version: 0.15.0
Summary: BIDS integration into snakemake workflows
Project-URL: repository, https://github.com/khanlab/snakebids
Project-URL: documentation, https://snakebids.readthedocs.io/
Author-email: Ali Khan <alik@robarts.ca>, Peter Van Dyken <pvandyk2@uwo.ca>, Tristan Kuehn <tkuehn@uwo.ca>, Jason Kai <tkai@uwo.ca>
License-Expression: MIT
License-File: LICENSE
Requires-Python: <4.0,>=3.10
Requires-Dist: attrs>=22.2.0
Requires-Dist: boutiques>=0.5.25
Requires-Dist: copier>=9.2.0
Requires-Dist: docutils!=0.21.post1
Requires-Dist: importlib-resources>=5.12.0
Requires-Dist: jinja2-time>=0.2.0
Requires-Dist: lazy-loader>=0.3
Requires-Dist: more-itertools>=8
Requires-Dist: numpy>=1.23.2; python_version >= '3.11'
Requires-Dist: pandas>=2.1.1; python_version >= '3.12'
Requires-Dist: pluggy>=1.3
Requires-Dist: pvandyken-deprecated==0.0.4
Requires-Dist: pybids~=0.21.0
Requires-Dist: requests>=2.31.0
Requires-Dist: ruamel-yaml>=0.17.2
Requires-Dist: snakemake<8,>=5.28.0; python_version < '3.11'
Requires-Dist: snakemake>=7.18.2; python_version >= '3.11'
Requires-Dist: typing-extensions>=3.10.0
